dinghy/__init__.py
dinghy/__main__.py
dinghy/adhoc.py
dinghy/cli.py
dinghy/digest.py
dinghy/graphql_helpers.py
dinghy/helpers.py
dinghy/jinja_helpers.py
dinghy/graphql/author_frag.graphql
dinghy/graphql/comment_frag.graphql
dinghy/graphql/issue_comments.graphql
dinghy/graphql/issue_frag.graphql
dinghy/graphql/org_project_entries.graphql
dinghy/graphql/pr_comments.graphql
dinghy/graphql/pr_reviews.graphql
dinghy/graphql/pr_reviewthreads.graphql
dinghy/graphql/project_entries_frag.graphql
dinghy/graphql/pull_request_frag.graphql
dinghy/graphql/release_frag.graphql
dinghy/graphql/repo_frag.graphql
dinghy/graphql/repo_issues.graphql
dinghy/graphql/repo_pull_requests.graphql
dinghy/graphql/repo_releases.graphql
dinghy/graphql/review_comments.graphql
dinghy/graphql/review_frag.graphql
dinghy/graphql/reviewthread_comments.graphql
dinghy/graphql/reviewthread_frag.graphql
dinghy/graphql/search_entries.graphql
dinghy/templates/digest.html.j2
dinghy-1.4.1.dist-info/licenses/LICENSE.txt
dinghy-1.4.1.dist-info/METADATA
dinghy-1.4.1.dist-info/WHEEL
dinghy-1.4.1.dist-info/entry_points.txt
dinghy-1.4.1.dist-info/top_level.txt
dinghy-1.4.1.dist-info/RECORD
