Metadata-Version: 2.4
Name: dinghy
Version: 1.4.1
Summary: Dinghy daily digest tool
Author-email: Ned Batchelder <ned@nedbatchelder.com>
License-Expression: Apache-2.0
Project-URL: Mastodon, https://hachyderm.io/@nedbat
Project-URL: Funding, https://github.com/sponsors/nedbat
Project-URL: Issues, https://github.com/nedbat/dinghy/issues
Project-URL: Source, https://github.com/nedbat/dinghy
Project-URL: Home, https://github.com/nedbat/dinghy
Classifier: Development Status :: 5 - Production/Stable
Classifier: Intended Audience :: Developers
Classifier: Programming Language :: Python
Classifier: Programming Language :: Python :: 3
Classifier: Programming Language :: Python :: 3.9
Classifier: Programming Language :: Python :: 3.10
Classifier: Programming Language :: Python :: 3.11
Classifier: Programming Language :: Python :: 3.12
Classifier: Programming Language :: Python :: 3.13
Requires-Python: >=3.9
License-File: LICENSE.txt
Requires-Dist: aiofiles>=0.8
Requires-Dist: aiohttp>3
Requires-Dist: backports-datetime-fromisoformat; python_version < "3.11"
Requires-Dist: click>8
Requires-Dist: click-log>0.3
Requires-Dist: emoji
Requires-Dist: glom
Requires-Dist: jinja2>3
Requires-Dist: pyyaml>=6
Dynamic: license-file
